gradio_iframecomponent/__init__.py
gradio_iframecomponent/iframecomponent.py
gradio_iframecomponent/iframecomponent.pyi
gradio_iframecomponent/templates/component/index.js
gradio_iframecomponent/templates/component/style.css
gradio_iframecomponent/templates/example/index.js
gradio_iframecomponent/templates/example/style.css
gradio_iframecomponent-0.0.1.dist-info/METADATA
gradio_iframecomponent-0.0.1.dist-info/WHEEL
gradio_iframecomponent-0.0.1.dist-info/RECORD
